qingclient/__init__.py
qingclient/_version.py
qingclient/auth_service.py
qingclient/base_client.py
qingclient/msg_service.py
qingclient/token_service.py
qingclient/user_service.py
qingclient/types/__init__.py
qingclient/types/auth.py
qingclient/types/base.py
qingclient/types/msg.py
qingclient/types/user.py
qingclient/types/wx.py
qing_client-0.1.19.dist-info/METADATA
qing_client-0.1.19.dist-info/WHEEL
qing_client-0.1.19.dist-info/top_level.txt
qing_client-0.1.19.dist-info/RECORD
