Metadata-Version: 2.4
Name: qing-client
Version: 0.1.19
Summary: Python client for audit logging services
Author-email: xiaoyue9527 <xiaoyue9527@example.com>
License: MIT
Project-URL: homepage, https://github.com/yourusername/qing-client
Project-URL: Bug Tracker, https://github.com/yourusername/qing-client/issues
Project-URL: Documentation, https://github.com/yourusername/qing-client/wiki
Keywords: audit,logging,security,monitoring
Classifier: Programming Language :: Python :: 3
Classifier: License :: OSI Approved :: MIT License
Classifier: Operating System :: OS Independent
Requires-Python: >=3.7
Requires-Dist: httpx>=0.23.0
Requires-Dist: pydantic>=2.0.0
Provides-Extra: dev
Requires-Dist: pytest>=7.0; extra == "dev"
Requires-Dist: pytest-asyncio>=0.20.0; extra == "dev"
Requires-Dist: twine>=4.0.0; extra == "dev"
Requires-Dist: build>=0.10.0; extra == "dev"
Requires-Dist: bumpversion>=0.6.0; extra == "dev"
